<BackupInst xmlns="http://www.microsoft.com/GroupPolicy/GPOOperations/Manifest"><GPOGuid><![CDATA[{31B2F340-016D-11D2-945F-00C04FB984F9}]]></GPOGuid><GPODomain><![CDATA[Assengraaf.nl]]></GPODomain><GPODomainGuid><![CDATA[{d10372e3-7037-4aba-a7f5-443b073e300e}]]></GPODomainGuid><GPODomainController><![CDATA[AsSv1.Assengraaf.nl]]></GPODomainController><BackupTime><![CDATA[2015-11-25T09:30:24]]></BackupTime><ID><![CDATA[{A00694BC-B2B0-4120-B822-CDC6A9961453}]]></ID><Comment><![CDATA[]]></Comment><GPODisplayName><![CDATA[Default Domain Policy]]></GPODisplayName></BackupInst>
